{
    "backend": "api-server-nodejs",
    "db_name": "",
    "db_pass": "",
    "db_type": "sqlite",
    "db_user": "",
    "dbms": "1",
    "description": "generated product",
    "design": "material-kit",
    "docker": "1",
    "err_code": 0,
    "frontend": "react",
    "heroku": "0",
    "pattern": "fullstack",
    "pro": "0",
    "task_id": "eeee85fc-86a9-4336-a015-7fa7f28d7a54",
    "task_info": "Upload Sources [0%] - 320 files",
    "task_output": "eeee85fc-86a9-4336-a015-7fa7f28d7a54.zip",
    "task_result": "SUCCESS",
    "task_state": "RUNNING",
    "task_ts_end": "2023-04-29-11-51-47",
    "task_ts_start": "2023-04-29-11-51-45"
}